binance_bulk_downloader/__init__.py
binance_bulk_downloader/downloader.py
binance_bulk_downloader/exceptions.py
binance_bulk_downloader-1.1.0.1.dist-info/LICENSE
binance_bulk_downloader-1.1.0.1.dist-info/METADATA
binance_bulk_downloader-1.1.0.1.dist-info/WHEEL
binance_bulk_downloader-1.1.0.1.dist-info/top_level.txt
binance_bulk_downloader-1.1.0.1.dist-info/RECORD
